{
    "LANDING_PAGE_ANNOUNCEMENT_TEXT": "Introducing BlockScan: Real-time blockchain analytics at your fingertips",
    "LANDING_PAGE_HERO_TEXT": "Unlock the Power of Blockchain Data",
    "LANDING_PAGE_SUB_HERO_TEXT": "Stay ahead of the curve with our cutting-edge blockchain analysis tool. Dive deep into transactions, smart contracts, and network activity with ease and precision.",
    "STARTER_TEMPLATE_APPLICATION_NAME": "BlockChainSight",
    "STARTER_TEMPLATE_PLACEHOLDER_TABLE_ITEM_1": "Latest Block Analysis",
    "STARTER_TEMPLATE_PLACEHOLDER_TABLE_ITEM_2": "Transaction Trends",
    "STARTER_TEMPLATE_PLACEHOLDER_TABLE_ITEM_3": "New Token Alerts",
    "STARTER_TEMPLATE_PLACEHOLDER_TABLE_ITEM_4": "Smart Contract Updates",
    "STARTER_TEMPLATE_HERO_PRIMARY_TITLE": "Unlock Blockchain Insights",
    "STARTER_TEMPLATE_HERO_SECONDARY_TITLE": "Real-time analysis of new blockchain data at your fingertips",
    "STARTER_TEMPLATE_HERO_PRIMARY_BUTTON_TEXT": "Start Analyzing Now",
    "STARTER_TEMPLATE_HERO_SECONDARY_BUTTON_TEXT": "Learn More",
    "PAGE_DETAIL_1_KEY": "Real-Time Analysis",
    "PAGE_DETAIL_1_VALUE": "Instantly process and interpret new blockchain data as it emerges",
    "PAGE_DETAIL_2_KEY": "Comprehensive Insights",
    "PAGE_DETAIL_2_VALUE": "Extract valuable information from transactions, smart contracts, and network activities",
    "PAGE_DETAIL_3_KEY": "User-Friendly Interface",
    "PAGE_DETAIL_3_VALUE": "Easily navigate complex blockchain data with our intuitive dashboard and visualization tools",
    "FEATURE_1_TITLE": "Real-Time Blockchain Analysis",
    "FEATURE_1_BODY": "Stay ahead of the curve with instant insights on new blockchain data as it emerges.",
    "FEATURE_2_TITLE": "Custom Alert System",
    "FEATURE_2_BODY": "Set up personalized notifications for specific blockchain events or trends that matter to you.",
    "FEATURE_3_TITLE": "Interactive Data Visualization",
    "FEATURE_3_BODY": "Explore complex blockchain information through intuitive, easy-to-understand visual representations.",
    "FEATURE_4_TITLE": "Multi-Chain Support",
    "FEATURE_4_BODY": "Analyze and compare data across multiple blockchain networks in one unified platform.",
    "FEATURE_5_TITLE": "Advanced Pattern Recognition",
    "FEATURE_5_BODY": "Leverage AI-powered algorithms to identify emerging trends and anomalies in blockchain activity.",
    "FEATURE_6_TITLE": "Comprehensive Reporting",
    "FEATURE_6_BODY": "Generate detailed, customizable reports on blockchain metrics for informed decision-making.",
    "PLACEHOLDER_ITEMS_TABLE_TITLE": "Blockchain Analysis Package Options",
    "PLACEHOLDER_ITEM_1": "Basic Insights",
    "PLACEHOLDER_ITEM_2": "Pro Analytics",
    "PLACEHOLDER_ITEM_3": "Enterprise Suite",
    "PLACEHOLDER_ITEM_4": "Custom API Access",
    "PLACEHOLDER_ITEM_5": "Real-Time Alerts",
    "PLACEHOLDER_ITEM_6": "Historical Data",
    "PLACEHOLDER_ITEM_DESCRIPTION_1": "Essential blockchain metrics and transaction analysis",
    "PLACEHOLDER_ITEM_DESCRIPTION_2": "Advanced analytics with predictive modeling",
    "PLACEHOLDER_ITEM_DESCRIPTION_3": "Comprehensive analysis tools for large-scale operations",
    "PLACEHOLDER_ITEM_DESCRIPTION_4": "Tailored API integration for your specific needs",
    "PLACEHOLDER_ITEM_DESCRIPTION_5": "Instant notifications on significant blockchain events",
    "PLACEHOLDER_ITEM_DESCRIPTION_6": "Access to extensive blockchain data archives",
    "PLACEHOLDER_ITEM_PRICE_1": "$49.99/month",
    "PLACEHOLDER_ITEM_PRICE_2": "$99.99/month",
    "PLACEHOLDER_ITEM_PRICE_3": "$249.99/month",
    "PLACEHOLDER_ITEM_PRICE_4": "$199.99/month",
    "PLACEHOLDER_ITEM_PRICE_5": "$79.99/month",
    "PLACEHOLDER_ITEM_PRICE_6": "$149.99/month",
    "PLACEHOLDER_ITEMS_TOTAL_PRICE": "Customized package pricing available",
    "CONTACT_FORM_TITLE_PLACEHOLDER_TEXT": "Get Started with Blockchain Insights",
    "CONTACT_FORM_SUBTITLE_PLACEHOLDER_TEXT": "Unlock the power of blockchain data analysis",
    "CONTACT_FORM_TEXT_FIELD_PLACEHOLDER_TEXT_1": "Your Name",
    "CONTACT_FORM_TEXT_FIELD_PLACEHOLDER_TEXT_2": "Email Address",
    "CONTACT_FORM_TEXT_FIELD_PLACEHOLDER_TEXT_3": "Phone Number (Optional)",
    "CONTACT_FORM_TEXT_FIELD_PLACEHOLDER_TEXT_4": "Company Name",
    "CONTACT_FORM_TEXT_FIELD_PLACEHOLDER_TEXT_5": "Blockchain(s) of Interest",
    "CONTACT_FORM_TEXT_FIELD_PLACEHOLDER_TEXT_6": "Additional Comments or Requirements",
    "CONTACT_FORM_PLACEHOLDER_SERVICE_ITEM_1": "Real-time Blockchain Data Analysis",
    "CONTACT_FORM_PLACEHOLDER_SERVICE_ITEM_2": "Custom Analytics Dashboard",
    "CONTACT_FORM_PLACEHOLDER_SERVICE_ITEM_3": "Smart Contract Monitoring",
    "CONTACT_FORM_PLACEHOLDER_SERVICE_ITEM_4": "Trend Forecasting and Insights",
    "SIGN_UP_COMPONENT_CREATE_ACCOUNT_PLACEHOLDER_TEXT": "Join the blockchain revolution",
    "SIGN_UP_COMPONENT_ALREADY_HAVE_ACCOUNT_PLACEHOLDER_TEXT": "Already tracking the chain?",
    "SIGN_UP_COMPONENT_LOGIN_PLACEHOLDER_TEXT": "Access your insights",
    "SIGN_UP_COMPONENT_NAME_PLACEHOLDER_TEXT": "Your name (or favorite crypto alias)",
    "SIGN_UP_COMPONENT_EMAIL_PLACEHOLDER_TEXT": "Email for blockchain updates",
    "SIGN_UP_COMPONENT_PASSWORD_PLACEHOLDER_TEXT": "Secure password (as unbreakable as blockchain)",
    "SIGN_UP_COMPONENT_CREATE_ACCOUNT_BUTTON_PLACEHOLDER_TEXT": "Launch My Blockchain Analysis",
    "SIGN_UP_COMPONENT_ADD_ACCOUNT_BUTTON_PLACEHOLDER_TEXT": "Add Another Wallet",
    "SIGN_UP_COMPONENT_GOOGLE_PLACEHOLDER_TEXT": "Quick Sign-Up with Google",
    "FAQ_TITLE_PLACEHOLDER_TEXT": "Frequently Asked Questions",
    "FAQ_SUBTITLE_PLACEHOLDER_TEXT": "Everything you need to know about our blockchain analysis app",
    "FAQ_PLACEHOLDER_QUESTION_TEXT_1": "What is this blockchain analysis app?",
    "FAQ_PLACEHOLDER_ANSWER_TEXT_1": "Our app is a powerful tool designed to analyze new blockchain information in real-time. It provides insights, trends, and detailed analytics to help users make informed decisions in the crypto space.",
    "FAQ_PLACEHOLDER_QUESTION_TEXT_2": "How does the app work?",
    "FAQ_PLACEHOLDER_ANSWER_TEXT_2": "The app connects to multiple blockchain networks, continuously fetches new data, and uses advanced algorithms to analyze transactions, smart contracts, and network activities. It then presents this information in easy-to-understand charts, graphs, and reports.",
    "FAQ_PLACEHOLDER_QUESTION_TEXT_3": "Who can benefit from using this app?",
    "FAQ_PLACEHOLDER_ANSWER_TEXT_3": "Our app is valuable for a wide range of users, including cryptocurrency traders, blockchain developers, researchers, and financial analysts. Anyone interested in gaining deeper insights into blockchain activities can benefit from our tool.",
    "FAQ_PLACEHOLDER_QUESTION_TEXT_4": "What features does the app offer?",
    "FAQ_PLACEHOLDER_ANSWER_TEXT_4": "Key features include real-time transaction monitoring, smart contract analysis, wallet tracking, market trend predictions, customizable alerts, and comprehensive reporting. We also offer API access for integration with other tools and platforms.",
    "FAQ_PLACEHOLDER_QUESTION_TEXT_5": "Is the app suitable for beginners?",
    "FAQ_PLACEHOLDER_ANSWER_TEXT_5": "Absolutely! While our app offers advanced features for experienced users, we've designed the interface to be intuitive and user-friendly. We provide tutorials, tooltips, and a comprehensive knowledge base to help beginners get started with blockchain analysis.",
    "PLACEHOLDER_FAQ_TITLE": "Frequently Asked Questions",
    "ACCORDION_QUESTION_1": "What is this blockchain analysis app?",
    "ACCORDION_ANSWER_1": "Our app is a powerful tool designed to analyze and interpret new blockchain information in real-time, providing users with valuable insights and data visualization for informed decision-making.",
    "ACCORDION_QUESTION_2": "How does the app process new blockchain data?",
    "ACCORDION_ANSWER_2": "The app continuously scans blockchain networks, processes incoming transactions and smart contract interactions, and applies advanced algorithms to extract meaningful patterns and trends from the raw data.",
    "ACCORDION_QUESTION_3": "What kind of insights can I gain from using this app?",
    "ACCORDION_ANSWER_3": "Users can gain insights such as transaction volume trends, wallet activity analysis, token distribution patterns, smart contract usage statistics, and early detection of emerging blockchain phenomena or potential security risks.",
    "ACCORDION_QUESTION_4": "Is this app suitable for both beginners and experienced blockchain analysts?",
    "ACCORDION_ANSWER_4": "Yes, our app is designed with an intuitive interface for beginners, while also offering advanced features and customizable analysis tools to satisfy the needs of experienced blockchain analysts and researchers.",
    "STARTER_TEMPLATE_FOOTER_CONTENT": "\u00a9 2023 BlockChainSight. Empowering blockchain analysis with real-time insights.",
    "CTA_TITLE": "Unlock Blockchain Insights",
    "CTA_BODY": "Stay ahead of the curve with real-time blockchain analysis",
    "CTA_SUBTITLE": "Empower Your Decisions",
    "CTA_CONTENT_SUBTITLE": "Dive Deep into New Blockchain Data",
    "TESTIMONIAL_SECTION_TITLE_PLACEHOLDER_TEXT": "What Our Users Are Saying",
    "TESTIMONIAL_SECTION_SUBTITLE_PLACEHOLDER_TEXT": "Discover how our blockchain analysis app is transforming the way people understand crypto markets",
    "TESTIMONIAL_1_PLACEHOLDER_TEXT": "This app has revolutionized how I track and analyze blockchain data. It's become an indispensable tool for my crypto investments.",
    "TESTIMONIAL_GIVER_1_PLACEHOLDER_TEXT": "Sarah Chen",
    "TESTIMONIAL_GIVER_1_DESCRIPTION_PLACEHOLDER_TEXT": "Crypto Analyst, BlockChain Ventures",
    "TESTIMONIAL_2_PLACEHOLDER_TEXT": "The real-time insights and user-friendly interface make complex blockchain data accessible and actionable. A game-changer for our research team.",
    "TESTIMONIAL_GIVER_2_PLACEHOLDER_TEXT": "Dr. Marcus Johnson",
    "TESTIMONIAL_GIVER_2_DESCRIPTION_PLACEHOLDER_TEXT": "Head of Research, CryptoTech Institute",
    "TESTIMONIAL_3_PLACEHOLDER_TEXT": "As a blockchain developer, this app has significantly improved my ability to debug and optimize smart contracts. It's like having x-ray vision for the blockchain.",
    "TESTIMONIAL_GIVER_3_PLACEHOLDER_TEXT": "Alex Rodriguez",
    "TESTIMONIAL_GIVER_3_DESCRIPTION_PLACEHOLDER_TEXT": "Senior Blockchain Developer, DecentralizeNow",
    "FOOTER_COMPONENT_1_FOOTER_TEXT_1": "\u00a9 2023 BlockchainInsight. All rights reserved.",
    "FOOTER_COMPONENT_1_TITLE_TEXT": "About BlockchainInsight",
    "FOOTER_COMPONENT_1_BODY_TEXT_1": "Real-time blockchain analysis",
    "FOOTER_COMPONENT_1_BODY_TEXT_2": "Advanced data visualization",
    "FOOTER_COMPONENT_1_BODY_TEXT_3": "Customizable alerts",
    "FOOTER_COMPONENT_1_BODY_TEXT_4": "Multi-chain support",
    "FOOTER_COMPONENT_2_TITLE_TEXT": "Resources",
    "FOOTER_COMPONENT_2_BODY_TEXT_1": "Documentation",
    "FOOTER_COMPONENT_2_BODY_TEXT_2": "API Reference",
    "FOOTER_COMPONENT_2_BODY_TEXT_3": "Tutorials",
    "FOOTER_COMPONENT_2_BODY_TEXT_4": "Blog",
    "FOOTER_COMPONENT_3_TITLE_TEXT": "Connect",
    "FOOTER_COMPONENT_3_BODY_TEXT_1": "Twitter",
    "FOOTER_COMPONENT_3_BODY_TEXT_2": "Discord",
    "FOOTER_COMPONENT_3_BODY_TEXT_3": "GitHub",
    "FOOTER_COMPONENT_3_BODY_TEXT_4": "Contact Us",
    "SIDEBAR_BOTTOM_PLACEHOLDER_TEXT": "Blockchain Insights",
    "SIDEBAR_BOTTOM_SUBTEXT_PLACEHOLDER_TEXT": "Stay ahead with real-time analytics",
    "SIDEBAR_NAVIGATION_PLACEHOLDER_TEXT_1": "Dashboard",
    "SIDEBAR_NAVIGATION_PLACEHOLDER_TEXT_2": "Transaction Analysis",
    "SIDEBAR_NAVIGATION_PLACEHOLDER_TEXT_3": "Block Explorer",
    "SIDEBAR_NAVIGATION_PLACEHOLDER_TEXT_4": "Network Stats",
    "SIDEBAR_FOOTER_PLACEHOLDER_TEXT_1": "Settings",
    "SIDEBAR_FOOTER_PLACEHOLDER_TEXT_2": "Help Center",
    "SIDEBAR_FOOTER_PLACEHOLDER_TEXT_3": "Contact Support",
    "HERO_TEXT_BEFORE_TITLE": "Introducing the Future of Blockchain Analytics",
    "HERO_TITLE": "CryptoInsight: Real-Time Blockchain Analysis at Your Fingertips",
    "HERO_SUBTITLE": "Stay ahead of the curve with instant insights into new blockchain data, trends, and transactions",
    "NEWSLETTER_TITLE_PLACEHOLDER_TEXT": "Stay Ahead of the Blockchain Curve",
    "NEWSLETTER_BUTTON_CTA_PLACEHOLDER_TEXT": "Get Blockchain Insights",
    "STARTER_TEMPLATE_CALL_TO_ACTION_TITLE": "Unlock Blockchain Insights",
    "STARTER_TEMPLATE_CALL_TO_ACTION_SUBTITLE": "Analyze new blockchain data in real-time with our powerful and user-friendly app",
    "STARTER_TEMPLATE_CALL_TO_ACTION_BUTTON_TEXT": "Start Analyzing Now",
    "PERSON_NAME": "BlockScan",
    "HEADER_NAVBAR_TEXT_1": "Dashboard",
    "HEADER_NAVBAR_TEXT_2": "Blockchain Explorer",
    "HEADER_NAVBAR_TEXT_3": "Analytics",
    "HEADER_NAVBAR_TEXT_4": "Alerts",
    "HEADER_NAVBAR_TEXT_5": "Documentation"
}